llama_stack_provider_trustyai_garak/__init__.py
llama_stack_provider_trustyai_garak/avid_report.py
llama_stack_provider_trustyai_garak/base_eval.py
llama_stack_provider_trustyai_garak/compat.py
llama_stack_provider_trustyai_garak/config.py
llama_stack_provider_trustyai_garak/constants.py
llama_stack_provider_trustyai_garak/errors.py
llama_stack_provider_trustyai_garak/provider.py
llama_stack_provider_trustyai_garak/result_utils.py
llama_stack_provider_trustyai_garak/shield_scan.py
llama_stack_provider_trustyai_garak/utils.py
llama_stack_provider_trustyai_garak/version_utils.py
llama_stack_provider_trustyai_garak/inline/__init__.py
llama_stack_provider_trustyai_garak/inline/garak_eval.py
llama_stack_provider_trustyai_garak/inline/provider.py
llama_stack_provider_trustyai_garak/remote/__init__.py
llama_stack_provider_trustyai_garak/remote/garak_remote_eval.py
llama_stack_provider_trustyai_garak/remote/provider.py
llama_stack_provider_trustyai_garak/remote/kfp_utils/__init__.py
llama_stack_provider_trustyai_garak/remote/kfp_utils/components.py
llama_stack_provider_trustyai_garak/remote/kfp_utils/pipeline.py
llama_stack_provider_trustyai_garak/remote/kfp_utils/utils.py
llama_stack_provider_trustyai_garak-0.1.8.dist-info/licenses/LICENSE
llama_stack_provider_trustyai_garak-0.1.8.dist-info/METADATA
llama_stack_provider_trustyai_garak-0.1.8.dist-info/WHEEL
llama_stack_provider_trustyai_garak-0.1.8.dist-info/top_level.txt
llama_stack_provider_trustyai_garak-0.1.8.dist-info/RECORD
