Metadata-Version: 2.4
Name: llama-stack-provider-trustyai-garak
Version: 0.1.8
Summary: Out-Of-Tree Llama Stack provider for Garak Red-teaming
Author: TrustyAI Team
Author-email: Sai Chandra Pandraju <saichandrapandraju@gmail.com>
License-Expression: Apache-2.0
Project-URL: homepage, https://github.com/trustyai-explainability/llama-stack-provider-trustyai-garak
Project-URL: repository, https://github.com/trustyai-explainability/llama-stack-provider-trustyai-garak
Keywords: llama-stack,garak,red-teaming,security,ai-safety
Requires-Python: >=3.12
License-File: LICENSE
Requires-Dist: llama-stack[client]>=0.4.0
Requires-Dist: kfp>=2.14.6
Requires-Dist: kfp-kubernetes>=2.14.6
Requires-Dist: kfp-server-api>=2.14.6
Requires-Dist: boto3>=1.35.88
Provides-Extra: inline
Requires-Dist: langchain==0.3.27; extra == "inline"
Requires-Dist: garak==0.12.0; extra == "inline"
Provides-Extra: dev
Requires-Dist: pytest; extra == "dev"
Requires-Dist: pytest-cov; extra == "dev"
Requires-Dist: pytest-asyncio; extra == "dev"
Requires-Dist: black; extra == "dev"
Requires-Dist: isort; extra == "dev"
Dynamic: license-file
